repo2docker/__init__.py
repo2docker/__main__.py
repo2docker/_version.py
repo2docker/app.py
repo2docker/docker.py
repo2docker/engine.py
repo2docker/semver.py
repo2docker/utils.py
repo2docker/buildpacks/__init__.py
repo2docker/buildpacks/_r_base.py
repo2docker/buildpacks/base.py
repo2docker/buildpacks/docker.py
repo2docker/buildpacks/python3-login
repo2docker/buildpacks/r.py
repo2docker/buildpacks/repo2docker-entrypoint
repo2docker/buildpacks/__pycache__/__init__.cpython-310.pyc
repo2docker/buildpacks/__pycache__/__init__.cpython-37.pyc
repo2docker/buildpacks/__pycache__/_r_base.cpython-310.pyc
repo2docker/buildpacks/__pycache__/_r_base.cpython-37.pyc
repo2docker/buildpacks/__pycache__/base.cpython-310.pyc
repo2docker/buildpacks/__pycache__/base.cpython-37.pyc
repo2docker/buildpacks/__pycache__/docker.cpython-310.pyc
repo2docker/buildpacks/__pycache__/docker.cpython-37.pyc
repo2docker/buildpacks/__pycache__/r.cpython-310.pyc
repo2docker/buildpacks/__pycache__/r.cpython-37.pyc
repo2docker/buildpacks/conda/__init__.py
repo2docker/buildpacks/conda/activate-conda.sh
repo2docker/buildpacks/conda/environment.lock
repo2docker/buildpacks/conda/environment.py-2.7.lock
repo2docker/buildpacks/conda/environment.py-2.7.yml
repo2docker/buildpacks/conda/environment.py-3.5.lock
repo2docker/buildpacks/conda/environment.py-3.5.yml
repo2docker/buildpacks/conda/environment.py-3.6.lock
repo2docker/buildpacks/conda/environment.py-3.6.yml
repo2docker/buildpacks/conda/environment.py-3.7.lock
repo2docker/buildpacks/conda/environment.py-3.7.yml
repo2docker/buildpacks/conda/environment.py-3.8.lock
repo2docker/buildpacks/conda/environment.py-3.8.yml
repo2docker/buildpacks/conda/environment.py-3.9.lock
repo2docker/buildpacks/conda/environment.py-3.9.yml
repo2docker/buildpacks/conda/environment.yml
repo2docker/buildpacks/conda/freeze.py
repo2docker/buildpacks/conda/install-base-env.bash
repo2docker/buildpacks/conda/requirements.py-3.5.pip
dws_repo2docker-2022.2.0.1.dist-info/LICENSE
dws_repo2docker-2022.2.0.1.dist-info/METADATA
dws_repo2docker-2022.2.0.1.dist-info/WHEEL
dws_repo2docker-2022.2.0.1.dist-info/entry_points.txt
dws_repo2docker-2022.2.0.1.dist-info/top_level.txt
dws_repo2docker-2022.2.0.1.dist-info/RECORD
